{
    "articles": [
        {
            "source": "Edsurge.com",
            "title": "Personalized Learning Is a Problem of Privilege",
            "url": "https://www.edsurge.com/news/2018-01-21-personalized-learning-is-a-problem-of-privilege"
        },
        {
            "source": "Microsoft.com",
            "title": "Closing the Gender divide in technology",
            "url": "https://blogs.msdn.microsoft.com/teachers/?p=13615"
        },
        {
            "source": "Upenn.edu",
            "title": "Diaspora, Indigenous, and Minority Education (DIME): Special Issue",
            "url": "http://call-for-papers.sas.upenn.edu/cfp/2018/03/27/diaspora-indigenous-and-minority-education-dime-special-issue"
        },
        {
            "source": "Ascd.org",
            "title": "Confronting Inequity / Assessment for Equity",
            "url": "http://www.ascd.org/publications/educational-leadership/feb18/vol75/num05/Assessment-for-Equity.aspx"
        },
        {
            "source": "Resilience.org",
            "title": "Countering the Fabrication Divide",
            "url": "http://www.resilience.org/stories/2018-01-17/countering-fabrication-divide/"
        },
        {
            "source": "Edweek.org",
            "title": "Education Re-imagined - Career Corner - Education Week",
            "url": "http://blogs.edweek.org/topschooljobs/careers/2018/02/education_re-imagined.html?utm_source=feedburner&utm_medium=feed&utm_campaign=Feed%3A+EducationWeekTechnology+%28Education+Week%3A+Technology%29"
        },
        {
            "source": "Gettingsmart.com",
            "title": "Inequity in Education is Your (and My) Responsibility",
            "url": "http://www.gettingsmart.com/2018/02/inequity-in-education-is-your-and-my-responsibility/"
        },
        {
            "source": "Upenn.edu",
            "title": "Diaspora, Indigenous, and Minority Education: Studies of Migration, Integration, Equity, and Cultural Survival (DIME) Special Issue: Role of Technology in Indigenous, Minority, and Diaspora Language Maintenance, Cultural Survival, and Curriculum Innova",
            "url": "http://call-for-papers.sas.upenn.edu/cfp/2018/03/27/diaspora-indigenous-and-minority-education-studies-of-migration-integration-equity"
        },
        {
            "source": "Thersa.org",
            "title": "Technology, equity and a networked approach",
            "url": "https://www.thersa.org/discover/publications-and-articles/rsa-blogs/2018/03/technology-equity-and-a-networked-approach"
        },
        {
            "source": "Edweek.org",
            "title": "Getting Youth Technology Use Right - Education Week",
            "url": "https://www.edweek.org/ew/articles/2018/03/21/getting-youth-technology-use-right.html"
        },
        {
            "source": "Edweek.org",
            "title": "States Slow to Adopt ESSA's Testing Flexibility - Education Week",
            "url": "https://www.edweek.org/ew/articles/2018/01/17/states-slow-to-adopt-essas-testing-flexibility.html"
        },
        {
            "source": "Edweek.org",
            "title": "EdTech and Equity: An Interview by Henry Jenkins - EdTech Researcher - Education Week",
            "url": "http://blogs.edweek.org/edweek/edtechresearcher/2018/01/edtech_and_equity_an_interview_by_henry_jenkins.html?utm_source=feedburner&utm_medium=feed&utm_campaign=Feed%3A+EducationWeekResearch+%28Education+Week%3A+Research%29"
        },
        {
            "source": "Edweek.org",
            "title": "EdTech and Equity: An Interview by Henry Jenkins - EdTech Researcher - Education Week",
            "url": "http://blogs.edweek.org/edweek/edtechresearcher/2018/01/edtech_and_equity_an_interview_by_henry_jenkins.html?utm_source=feedburner&utm_medium=feed&utm_campaign=Feed%3A+EducationWeekTechnology+%28Education+Week%3A+Technology%29"
        },
        {
            "source": "Edweek.org",
            "title": "Blended Learning (Re)Defined - Learning Deeply - Education Week",
            "url": "http://blogs.edweek.org/edweek/learning_deeply/2018/01/blended_learning_redefined.html?utm_source=feedburner&utm_medium=feed&utm_campaign=Feed%3A+EducationWeekResearch+%28Education+Week%3A+Research%29"
        },
        {
            "source": "Edweek.org",
            "title": "Blended Learning (Re)Defined - Learning Deeply - Education Week",
            "url": "http://blogs.edweek.org/edweek/learning_deeply/2018/01/blended_learning_redefined.html?utm_source=feedburner&utm_medium=feed&utm_campaign=Feed%3A+EducationWeekTechnology+%28Education+Week%3A+Technology%29"
        },
        {
            "source": "Prnewswire.com",
            "title": "McGraw-Hill Education Explores the Future of Education at SXSW EDU in 2018",
            "url": "https://www.prnewswire.com/news-releases/mcgraw-hill-education-explores-the-future-of-education-at-sxsw-edu-in-2018-300606430.html"
        },
        {
            "source": "Livemint.com",
            "title": "The class divide in Indian education system",
            "url": "http://www.livemint.com/Opinion/DuRPMPSqaaqCDLoNMgRAbL/The-class-divide-in-Indian-education-system.html"
        },
        {
            "source": "Theconversation.com",
            "title": "Here's how Canada can be a global leader in ethical AI",
            "url": "http://theconversation.com/heres-how-canada-can-be-a-global-leader-in-ethical-ai-90991"
        },
        {
            "source": "Indianexpress.com",
            "title": "In testing times",
            "url": "http://indianexpress.com/article/opinion/columns/entrance-exams-for-higher-education-india-jrf-test-net-exam-5094342/"
        },
        {
            "source": "Project-syndicate.org",
            "title": "Education in the Digital Age",
            "url": "https://www.project-syndicate.org/commentary/education-skills-needed-for-digital-age-by-koichi-hamada-2018-02"
        },
        {
            "source": "Seattletimes.com",
            "title": "Replacement of high school ISTEP exam delayed another year",
            "url": "https://www.seattletimes.com/nation-world/nation-politics/replacement-of-high-school-istep-exam-delayed-another-year/"
        },
        {
            "source": "Qz.com",
            "title": "India\u2019s elite IITs have a plan to fix their gender gap\u2014but will it work?",
            "url": "https://qz.com/1182509/indias-elite-iits-have-a-plan-to-fix-their-gender-gap-but-will-it-work/"
        },
        {
            "source": "Japantimes.co.jp",
            "title": "New entrance exam isn\u2019t the right answer",
            "url": "https://www.japantimes.co.jp/opinion/2018/02/20/commentary/japan-commentary/new-entrance-exam-isnt-right-answer/"
        },
        {
            "source": "Japantimes.co.jp",
            "title": "Education in the digital age",
            "url": "https://www.japantimes.co.jp/opinion/2018/02/26/commentary/japan-commentary/education-digital-age/"
        },
        {
            "source": "The Irish Times",
            "title": "Mind the gap: Tackling the class divide at third level",
            "url": "https://www.irishtimes.com/news/education/mind-the-gap-tackling-the-class-divide-at-third-level-1.3409340"
        },
        {
            "source": "Theroot.com",
            "title": "A Case for Educational Reparations for Formerly Incarcerated People",
            "url": "https://www.theroot.com/a-case-for-educational-reparations-for-formerly-incarce-1824261219"
        },
        {
            "source": "Edweek.org",
            "title": "EdTech and Equity: An Interview by Henry Jenkins",
            "url": "http://blogs.edweek.org/edweek/edtechresearcher/2018/01/edtech_and_equity_an_interview_by_henry_jenkins.html"
        },
        {
            "source": "Americanprogress.org",
            "title": "Systematic Inequality",
            "url": "https://www.americanprogress.org/issues/race/reports/2018/02/21/447051/systematic-inequality/"
        },
        {
            "source": "Livemint.com",
            "title": "She is offline:India\u2019s digital gender divide",
            "url": "http://www.livemint.com/Opinion/sD6mVqLAEa7cvfJtmdXXuO/She-is-offlineIndias-digital-gender-divide.html"
        },
        {
            "source": "Cloudtweaks.com",
            "title": "Bridging the educational divide\u2013How business networks level the playing field for those most in need",
            "url": "https://cloudtweaks.com/2018/03/educational-divide-business-networks-level-the-playing-field/"
        },
        {
            "source": "Edweek.org",
            "title": "The advantages of the self-motivated learner and the digital class - Career Corner - Education Week",
            "url": "http://blogs.edweek.org/topschooljobs/careers/2018/02/the_advantages_of_the_self-mot.html?utm_source=feedburner&utm_medium=feed&utm_campaign=Feed%3A+EducationWeekTechnology+%28Education+Week%3A+Technology%29"
        },
        {
            "source": "Ndtv.com",
            "title": "Expect Something Good In The Budget For Education Sector: HRD Minister",
            "url": "https://www.ndtv.com/education/budget-2018-by-finance-minister-arun-jaitley-on-february-1-expect-something-good-in-the-budget-for-e-1805019"
        },
        {
            "source": "Edweek.org",
            "title": "Personalized Learning Pilot Program Reports Gains in Literacy Scores - Digital Education - Education Week",
            "url": "http://blogs.edweek.org/edweek/DigitalEducation/2018/03/personalized_learning_pilot_gains_literacy_scores_leap_innovations.html?utm_source=feedburner&utm_medium=feed&utm_campaign=Feed%3A+EducationWeekResearch+%28Education+Week%3A+Research%29"
        },
        {
            "source": "Edweek.org",
            "title": "Teachers Show More Attention to White Men in Online Courses, Study Finds - Digital Education - Education Week",
            "url": "http://blogs.edweek.org/edweek/DigitalEducation/2018/03/teachers_show_more_attention_white_men_online_courses.html?utm_source=feedburner&utm_medium=feed&utm_campaign=Feed%3A+EducationWeekTechnology+%28Education+Week%3A+Technology%29"
        },
        {
            "source": "Edweek.org",
            "title": "Teachers Show More Attention to White Men in Online Courses, Study Finds - Digital Education - Education Week",
            "url": "http://blogs.edweek.org/edweek/DigitalEducation/2018/03/teachers_show_more_attention_white_men_online_courses.html?utm_source=feedburner&utm_medium=feed&utm_campaign=Feed%3A+EducationWeekResearch+%28Education+Week%3A+Research%29"
        },
        {
            "source": "Sys-con.com",
            "title": "McGraw-Hill Education Explores the Future of Education at SXSW EDU in 2018",
            "url": "http://news.sys-con.com/node/4240148"
        },
        {
            "source": "The New York Times",
            "title": "Letters: The Battle Over Screen Time",
            "url": "https://www.nytimes.com/2018/02/24/opinion/sunday/digital-divide.html"
        },
        {
            "source": "Roanoke.com",
            "title": "Report: Poverty, rural schools among key education issues",
            "url": "http://www.roanoke.com/news/virginia/wire/report-poverty-rural-schools-among-key-education-issues/article_ca39b2c5-6cdc-5492-a6b6-0d2aefe2b850.html"
        },
        {
            "source": "Npr.org",
            "title": "Students March; DeVos Gets Grilled; The Funding Gap Widens",
            "url": "https://www.npr.org/sections/ed/2018/03/24/595237638/students-march-devos-gets-grilled-the-funding-gap-widens"
        },
        {
            "source": "Theconversation.com",
            "title": "Australia's digital divide is not going away",
            "url": "http://theconversation.com/australias-digital-divide-is-not-going-away-91834"
        },
        {
            "source": "Fee.org",
            "title": "Great Books May Revolutionize College Admissions Tests",
            "url": "https://fee.org/articles/great-books-may-revolutionize-college-admissions-tests/"
        },
        {
            "source": "Edweek.org",
            "title": "State Policy Implementation: An Imperative for Equity - Learning Deeply - Education Week",
            "url": "http://blogs.edweek.org/edweek/learning_deeply/2018/03/state_policy_implementation_an_imperative_for_equity.html?utm_source=feedburner&utm_medium=feed&utm_campaign=Feed%3A+EducationWeekResearch+%28Education+Week%3A+Research%29"
        },
        {
            "source": "Brookings.edu",
            "title": "Innovation to leapfrog educational progress in Latin America",
            "url": "http://www.brookings.edu/research/innovation-to-leapfrog-educational-progress-in-latin-america/"
        },
        {
            "source": "Edweek.org",
            "title": "Student-Centered Learning and Inclusion: Getting the Details Right - Learning Deeply - Education Week",
            "url": "http://blogs.edweek.org/edweek/learning_deeply/2018/03/student-centered_learning_and_inclusion_getting_the_details_right.html?utm_source=feedburner&utm_medium=feed&utm_campaign=Feed%3A+EducationWeekELearning+%28Education+Week%3A+E-Learning%29"
        },
        {
            "source": "Typepad.com",
            "title": "Stanford Study: Race And Gender Bias In Online Courses",
            "url": "http://taxprof.typepad.com/taxprof_blog/2018/04/stanford-study-race-and-gender-bias-in-online-courses.html"
        },
        {
            "source": "Acm.org",
            "title": "Leveraging Afrofuturism in human-centered design: A way forward",
            "url": "http://interactions.acm.org/blog/view/leveraging-afrofuturism-in-human-centered-design-a-way-forward"
        },
        {
            "source": "Edweek.org",
            "title": "Student-Centered Learning and Inclusion: Getting the Details Right - Learning Deeply - Education Week",
            "url": "http://blogs.edweek.org/edweek/learning_deeply/2018/03/student-centered_learning_and_inclusion_getting_the_details_right.html?utm_source=feedburner&utm_medium=feed&utm_campaign=Feed%3A+EducationWeekTechnology+%28Education+Week%3A+Technology%29"
        },
        {
            "source": "Edweek.org",
            "title": "Student-Centered Learning and Inclusion: Getting the Details Right - Learning Deeply - Education Week",
            "url": "http://blogs.edweek.org/edweek/learning_deeply/2018/03/student-centered_learning_and_inclusion_getting_the_details_right.html?utm_source=feedburner&utm_medium=feed&utm_campaign=Feed%3A+EducationWeekResearch+%28Education+Week%3A+Research%29"
        },
        {
            "source": "Jagranjosh.com",
            "title": "National Information Technology Exam 2018 Offers Fancy Gadgets to Winners",
            "url": "https://www.jagranjosh.com/articles/national-information-technology-exam-2018-offers-fancy-gadgets-to-winners-1517926335-1"
        },
        {
            "source": "Thehindubusinessline.com",
            "title": "Budget 2018: From black boards to digital boards",
            "url": "http://www.thehindubusinessline.com/economy/budget/budget-2018-from-black-boards-to-digital-boards/article22621265.ece"
        },
        {
            "source": "Edweek.org",
            "title": "Why Don't We See More Cognitive Science in Education? - Rick Hess Straight Up - Education Week",
            "url": "http://blogs.edweek.org/edweek/rick_hess_straight_up/2018/03/why_dont_we_see_more_cognitive_science_in_education.html?utm_source=feedburner&utm_medium=feed&utm_campaign=Feed%3A+EducationWeekResearch+%28Education+Week%3A+Research%29"
        },
        {
            "source": "Richmond.com",
            "title": "Report: Poverty, rural schools among key education issues",
            "url": "http://www.richmond.com/news/ap/report-poverty-rural-schools-among-key-education-issues/article_7bb97ebb-8363-533d-a494-93ee15a0d1fb.html"
        },
        {
            "source": "Dianeravitch.net",
            "title": "Indiana: Total Confusion on Which Standardized Test to Use",
            "url": "https://dianeravitch.net/2018/03/22/indiana-total-confusion-on-which-standardized-test-to-use/"
        },
        {
            "source": "Europa.eu",
            "title": "Specific actions form the Digital Education Action Plan",
            "url": "https://ec.europa.eu/digital-single-market/en/news/specific-actions-form-digital-education-action-plan"
        },
        {
            "source": "The Guardian (AU)",
            "title": "The Observer view on the continuing gender pay divide | Observer editorial",
            "url": "https://www.theguardian.com/commentisfree/2018/mar/10/observer-view-continuing-gender-pay-divide"
        },
        {
            "source": "Libsynpro.com",
            "title": "Closing the Digital Divide",
            "url": "http://windowsinsider.mpsn.libsynpro.com/closing-the-digital-divide"
        },
        {
            "source": "Sys-con.com",
            "title": "Bridging the educational divide\u2013How business networks level the playing field for those most in need",
            "url": "http://news.sys-con.com/node/4248779"
        },
        {
            "source": "Insidehighered.com",
            "title": "Study finds evidence of racial and gender bias in online education",
            "url": "https://www.insidehighered.com/news/2018/03/08/study-finds-evidence-racial-and-gender-bias-online-education"
        },
        {
            "source": "Knowyourmeme.com",
            "title": "Careerlinked Education Council",
            "url": "http://knowyourmeme.com/memes/sites/careerlinked-education-council"
        },
        {
            "source": "Eurekalert.org",
            "title": "Study reveals perceived gender bias against women is dominant factor in college major choice",
            "url": "https://www.eurekalert.org/pub_releases/2018-01/nyu-srp012218.php"
        },
        {
            "source": "Edweek.org",
            "title": "Teaching in the Tech Age - Career Corner - Education Week",
            "url": "http://blogs.edweek.org/topschooljobs/careers/2018/02/teaching_in_the_tech_age.html?utm_source=feedburner&utm_medium=feed&utm_campaign=Feed%3A+EducationWeekTechnology+%28Education+Week%3A+Technology%29"
        },
        {
            "source": "The Wall Street Journal",
            "title": "Double Standards Won't Close the Racial Learning Gap",
            "url": "https://www.wsj.com/articles/double-standards-wont-close-the-racial-learning-gap-1521585155"
        },
        {
            "source": "Psychologytoday.com",
            "title": "Educators Battle Discrimination in the Field",
            "url": "https://www.psychologytoday.com/us/blog/much-more-common-core/201804/educators-battle-discrimination-in-the-field"
        },
        {
            "source": "Edsurge.com",
            "title": "#DLNchat: How Will Net Neutrality Changes Affect Higher Education?",
            "url": "https://www.edsurge.com/news/2018-01-25-dlnchat-how-will-net-neutrality-changes-affect-higher-education"
        },
        {
            "source": "Edweek.org",
            "title": "Teachers on Tech: Good for Student Learning, Bad for Student Health - Digital Education - Education Week",
            "url": "http://blogs.edweek.org/edweek/DigitalEducation/2018/04/teachers_tech_gallup_survey.html?utm_source=feedburner&utm_medium=feed&utm_campaign=Feed%3A+EducationWeekTechnology+%28Education+Week%3A+Technology%29"
        },
        {
            "source": "Roanoke.com",
            "title": "Replacement of high school ISTEP exam delayed another year",
            "url": "http://www.roanoke.com/news/virginia/wire/replacement-of-high-school-istep-exam-delayed-another-year/article_90480f65-8ca6-53be-9dc6-23612f874ad4.html"
        },
        {
            "source": "Edweek.org",
            "title": "10 (More) Reasons Why the U.S. Education System Is Failing - Education Week",
            "url": "https://www.edweek.org/ew/articles/2018/01/29/10-more-reasons-why-the-us-education.html"
        },
        {
            "source": "Edweek.org",
            "title": "Access and Equity Through Career and Technical Education",
            "url": "http://blogs.edweek.org/edweek/global_learning/2018/04/access_and_equity_through_career_and_technical_education.html"
        },
        {
            "source": "Seattletimes.com",
            "title": "Illinois education board mulls expanding free testing",
            "url": "https://www.seattletimes.com/nation-world/illinois-education-board-mulls-expanding-free-testing/"
        },
        {
            "source": "Europa.eu",
            "title": "Increase in gender gap in the digital sector - Study on Women in the Digital Age",
            "url": "https://ec.europa.eu/digital-single-market/en/news/increase-gender-gap-digital-sector-study-women-digital-age"
        },
        {
            "source": "Nypost.com",
            "title": "Record number of city students took the SATs last year",
            "url": "https://nypost.com/2018/01/11/record-number-of-city-students-took-the-sats-last-year/"
        },
        {
            "source": "Un.org",
            "title": "Speakers Highlight National Strategies to End Gender Divide in Media, Digital Decision-Making, as Women\u2019s Commission Continues Sessions",
            "url": "https://www.un.org/press/en/2018/wom2139.doc.htm"
        },
        {
            "source": "Un.org",
            "title": "Speakers Highlight National Strategies to End Gender Divide in Media, Digital Decision-Making, as Women\u2019s Commission Continues Sessions",
            "url": "https://www.un.org/press/en/2018/wom2139.doc.htm-0"
        },
        {
            "source": "Nydailynews.com",
            "title": "Fewer girls than boys accepted into top N.Y. high schools",
            "url": "http://www.nydailynews.com/new-york/education/girls-boys-accepted-top-n-y-high-schools-article-1.3874754"
        },
        {
            "source": "Prnewswire.com",
            "title": "Gale and NC LIVE Help North Carolinians Prepare for College and Career Advancement",
            "url": "https://www.prnewswire.com/news-releases/gale-and-nc-live-help-north-carolinians-prepare-for-college-and-career-advancement-300583280.html"
        },
        {
            "source": "The Irish Times",
            "title": "\u2018Tackling the class divide at third level\u2019",
            "url": "https://www.irishtimes.com/opinion/letters/tackling-the-class-divide-at-third-level-1.3420430"
        },
        {
            "source": "Seattletimes.com",
            "title": "Report: Poverty, rural schools among key education issues",
            "url": "https://www.seattletimes.com/nation-world/report-poverty-rural-schools-among-key-education-issues/"
        },
        {
            "source": "Pib.nic.in",
            "title": "Digital education and literacy",
            "url": "http://pib.nic.in/newsite/PrintRelease.aspx?relid=177161"
        },
        {
            "source": "Phys.org",
            "title": "Web-based teaching can improve science understanding for struggling pupils",
            "url": "https://phys.org/news/2018-02-web-based-science-struggling-pupils.html"
        },
        {
            "source": "Dailycaller.com",
            "title": "SHERIFF DAVID CLARKE: School Choice Is Closing The Education Gap",
            "url": "http://dailycaller.com/2018/01/24/sheriff-david-clarke-school-choice-is-closing-the-education-gap/"
        },
        {
            "source": "Europa.eu",
            "title": "Education and training initiatives",
            "url": "http://europa.eu/rapid/press-release_MEMO-18-103_en.htm?locale=en"
        },
        {
            "source": "Ndtv.com",
            "title": "As Cities Look to Bridge Digital Divide, Is There a Hack for Inequality?",
            "url": "https://gadgets.ndtv.com/internet/features/as-cities-look-to-bridge-digital-divide-is-there-a-hack-for-inequality-1808880"
        },
        {
            "source": "Theconversation.com",
            "title": "Can education become truly egalitarian worldwide?",
            "url": "http://theconversation.com/can-education-become-truly-egalitarian-worldwide-90499"
        },
        {
            "source": "Pehub.com",
            "title": "Yogome takes in $26.9 mln Series B",
            "url": "https://www.pehub.com/2018/03/yogome-takes-26-9-mln-series-b/"
        },
        {
            "source": "Xconomy.com",
            "title": "Credtech Report Card: HackerRank, CodeFights, Credly, ACT, More",
            "url": "https://www.xconomy.com/san-francisco/2018/02/28/credtech-report-card-hackerrank-codefights-credly-act-more/"
        },
        {
            "source": "Harvard.edu",
            "title": "Education Without Learning?",
            "url": "https://www.gse.harvard.edu/news/uk/18/03/education-without-learning"
        },
        {
            "source": "Teachthought.com",
            "title": "30 Of The Most Popular Trends In Education",
            "url": "https://www.teachthought.com/the-future-of-learning/most-popular-trends-in-education/"
        },
        {
            "source": "The New York Times",
            "title": "An Advocate for Israel Draws Fire as He Nears Confirmation to Civil Rights Post",
            "url": "https://www.nytimes.com/2018/01/18/us/politics/kenneth-marcus-civil-rights-israel-bds.html"
        },
        {
            "source": "Roanoke.com",
            "title": "Illinois education board mulls expanding free testing",
            "url": "http://www.roanoke.com/news/virginia/wire/illinois-education-board-mulls-expanding-free-testing/article_bea853a1-9b2e-5725-b756-dda11713e365.html"
        },
        {
            "source": "Typepad.com",
            "title": "Weekly Legal Education Roundup",
            "url": "http://taxprof.typepad.com/taxprof_blog/2018/02/weekly-legal-education-roundup-1.html"
        },
        {
            "source": "The Hindu",
            "title": "On the digital highway",
            "url": "http://www.thehindu.com/education/on-the-digital-highway/article22917060.ece"
        },
        {
            "source": "Prnewsonline.com",
            "title": "Coordinator of Experiential Education and Internships (Coordinator of Cooperative Education)",
            "url": "https://jobs.prnewsonline.com/job/coordinator-of-experiential-education-and-internships-coordinator-of-cooperative-education/40257535/"
        },
        {
            "source": "Psychologytoday.com",
            "title": "Hiring for Equity",
            "url": "https://www.psychologytoday.com/blog/justice-in-the-classroom/201802/hiring-equity"
        },
        {
            "source": "Livemint.com",
            "title": "Is NEXT the panacea for medical education woes?",
            "url": "https://www.livemint.com/Education/MkZvFhKf39vIbKXmlDEfwK/Is-NEXT-the-panacea-for-medical-education-woes.html"
        },
        {
            "source": "Edweek.org",
            "title": "Why Don't We See More Cognitive Science in Education?",
            "url": "http://blogs.edweek.org/edweek/rick_hess_straight_up/2018/03/why_dont_we_see_more_cognitive_science_in_education.html"
        },
        {
            "source": "Ndtv.com",
            "title": "Open School, Private Students Not Allowed To Appear In NEET 2018",
            "url": "https://www.ndtv.com/education/neet-2018-notification-cbseneet-nic-in-open-school-not-allowed-check-eligibility-date-application-1810363"
        },
        {
            "source": "Bostonglobe.com",
            "title": "Despite gains, \u2018motherhood penalty\u2019 persists",
            "url": "https://www.bostonglobe.com/business/2018/03/12/despite-gains-motherhood-penalty-persists/xRCdHOnGl3EMcxmCj29pJL/story.html"
        },
        {
            "source": "Gartner.com",
            "title": "Davos Discussions: Technology\u2019s Role in Diversity and Inclusion",
            "url": "https://blogs.gartner.com/peter-sondergaard/davos-discussions-technologys-role-in-diversity-and-inclusion/"
        },
        {
            "source": "Msmagazine.com",
            "title": "Hacking for Inclusion: MIT Students Are Fighting Inequality with Technology",
            "url": "http://msmagazine.com/blog/2018/03/09/hacking-for-inclusion/"
        }
    ]
}
